Workbook

Sheet Summary
A1: Section | B1: Tests | C1: Pass | D1: Fail | E1: Blocked | F1: N/A | G1: Not run | H1: % done
A2: 00 Setup & smoke | B2: =COUNTIF(Tests!$B:$B,$A2) -> 9 | C2: =COUNTIFS(Tests!$B:$B,$A2,Tests!$H:$H,"Pass") -> 0 | D2: =COUNTIFS(Tests!$B:$B,$A2,Tests!$H:$H,"Fail") -> 0 | E2: =COUNTIFS(Tests!$B:$B,$A2,Tests!$H:$H,"Blocked") -> 0 | F2: =COUNTIFS(Tests!$B:$B,$A2,Tests!$H:$H,"N/A") -> 0 | G2: =COUNTIFS(Tests!$B:$B,$A2,Tests!$H:$H,"Not run") -> 9 | H2: =IF(B2=0,0,(B2-G2)/B2) -> 0
A3: 01 Registration | B3: =COUNTIF(Tests!$B:$B,$A3) -> 20 | C3: =COUNTIFS(Tests!$B:$B,$A3,Tests!$H:$H,"Pass") -> 0 | D3: =COUNTIFS(Tests!$B:$B,$A3,Tests!$H:$H,"Fail") -> 0 | E3: =COUNTIFS(Tests!$B:$B,$A3,Tests!$H:$H,"Blocked") -> 0 | F3: =COUNTIFS(Tests!$B:$B,$A3,Tests!$H:$H,"N/A") -> 0 | G3: =COUNTIFS(Tests!$B:$B,$A3,Tests!$H:$H,"Not run") -> 20 | H3: =IF(B3=0,0,(B3-G3)/B3) -> 0
A4: 02 Login & security | B4: =COUNTIF(Tests!$B:$B,$A4) -> 24 | C4: =COUNTIFS(Tests!$B:$B,$A4,Tests!$H:$H,"Pass") -> 0 | D4: =COUNTIFS(Tests!$B:$B,$A4,Tests!$H:$H,"Fail") -> 0 | E4: =COUNTIFS(Tests!$B:$B,$A4,Tests!$H:$H,"Blocked") -> 0 | F4: =COUNTIFS(Tests!$B:$B,$A4,Tests!$H:$H,"N/A") -> 0 | G4: =COUNTIFS(Tests!$B:$B,$A4,Tests!$H:$H,"Not run") -> 24 | H4: =IF(B4=0,0,(B4-G4)/B4) -> 0
A5: 03 Shop browsing & filters | B5: =COUNTIF(Tests!$B:$B,$A5) -> 38 | C5: =COUNTIFS(Tests!$B:$B,$A5,Tests!$H:$H,"Pass") -> 0 | D5: =COUNTIFS(Tests!$B:$B,$A5,Tests!$H:$H,"Fail") -> 0 | E5: =COUNTIFS(Tests!$B:$B,$A5,Tests!$H:$H,"Blocked") -> 0 | F5: =COUNTIFS(Tests!$B:$B,$A5,Tests!$H:$H,"N/A") -> 0 | G5: =COUNTIFS(Tests!$B:$B,$A5,Tests!$H:$H,"Not run") -> 38 | H5: =IF(B5=0,0,(B5-G5)/B5) -> 0
A6: 04 Cart | B6: =COUNTIF(Tests!$B:$B,$A6) -> 10 | C6: =COUNTIFS(Tests!$B:$B,$A6,Tests!$H:$H,"Pass") -> 0 | D6: =COUNTIFS(Tests!$B:$B,$A6,Tests!$H:$H,"Fail") -> 0 | E6: =COUNTIFS(Tests!$B:$B,$A6,Tests!$H:$H,"Blocked") -> 0 | F6: =COUNTIFS(Tests!$B:$B,$A6,Tests!$H:$H,"N/A") -> 0 | G6: =COUNTIFS(Tests!$B:$B,$A6,Tests!$H:$H,"Not run") -> 10 | H6: =IF(B6=0,0,(B6-G6)/B6) -> 0
A7: 05 Checkout | B7: =COUNTIF(Tests!$B:$B,$A7) -> 13 | C7: =COUNTIFS(Tests!$B:$B,$A7,Tests!$H:$H,"Pass") -> 0 | D7: =COUNTIFS(Tests!$B:$B,$A7,Tests!$H:$H,"Fail") -> 0 | E7: =COUNTIFS(Tests!$B:$B,$A7,Tests!$H:$H,"Blocked") -> 0 | F7: =COUNTIFS(Tests!$B:$B,$A7,Tests!$H:$H,"N/A") -> 0 | G7: =COUNTIFS(Tests!$B:$B,$A7,Tests!$H:$H,"Not run") -> 13 | H7: =IF(B7=0,0,(B7-G7)/B7) -> 0
A8: 06 Payment & placing orders | B8: =COUNTIF(Tests!$B:$B,$A8) -> 13 | C8: =COUNTIFS(Tests!$B:$B,$A8,Tests!$H:$H,"Pass") -> 0 | D8: =COUNTIFS(Tests!$B:$B,$A8,Tests!$H:$H,"Fail") -> 0 | E8: =COUNTIFS(Tests!$B:$B,$A8,Tests!$H:$H,"Blocked") -> 0 | F8: =COUNTIFS(Tests!$B:$B,$A8,Tests!$H:$H,"N/A") -> 0 | G8: =COUNTIFS(Tests!$B:$B,$A8,Tests!$H:$H,"Not run") -> 13 | H8: =IF(B8=0,0,(B8-G8)/B8) -> 0
A9: 07 My Orders | B9: =COUNTIF(Tests!$B:$B,$A9) -> 16 | C9: =COUNTIFS(Tests!$B:$B,$A9,Tests!$H:$H,"Pass") -> 0 | D9: =COUNTIFS(Tests!$B:$B,$A9,Tests!$H:$H,"Fail") -> 0 | E9: =COUNTIFS(Tests!$B:$B,$A9,Tests!$H:$H,"Blocked") -> 0 | F9: =COUNTIFS(Tests!$B:$B,$A9,Tests!$H:$H,"N/A") -> 0 | G9: =COUNTIFS(Tests!$B:$B,$A9,Tests!$H:$H,"Not run") -> 16 | H9: =IF(B9=0,0,(B9-G9)/B9) -> 0
A10: 08 Account settings | B10: =COUNTIF(Tests!$B:$B,$A10) -> 11 | C10: =COUNTIFS(Tests!$B:$B,$A10,Tests!$H:$H,"Pass") -> 0 | D10: =COUNTIFS(Tests!$B:$B,$A10,Tests!$H:$H,"Fail") -> 0 | E10: =COUNTIFS(Tests!$B:$B,$A10,Tests!$H:$H,"Blocked") -> 0 | F10: =COUNTIFS(Tests!$B:$B,$A10,Tests!$H:$H,"N/A") -> 0 | G10: =COUNTIFS(Tests!$B:$B,$A10,Tests!$H:$H,"Not run") -> 11 | H10: =IF(B10=0,0,(B10-G10)/B10) -> 0
A11: 09 Live chat (shop) | B11: =COUNTIF(Tests!$B:$B,$A11) -> 12 | C11: =COUNTIFS(Tests!$B:$B,$A11,Tests!$H:$H,"Pass") -> 0 | D11: =COUNTIFS(Tests!$B:$B,$A11,Tests!$H:$H,"Fail") -> 0 | E11: =COUNTIFS(Tests!$B:$B,$A11,Tests!$H:$H,"Blocked") -> 0 | F11: =COUNTIFS(Tests!$B:$B,$A11,Tests!$H:$H,"N/A") -> 0 | G11: =COUNTIFS(Tests!$B:$B,$A11,Tests!$H:$H,"Not run") -> 12 | H11: =IF(B11=0,0,(B11-G11)/B11) -> 0
A12: 10 Role access | B12: =COUNTIF(Tests!$B:$B,$A12) -> 8 | C12: =COUNTIFS(Tests!$B:$B,$A12,Tests!$H:$H,"Pass") -> 0 | D12: =COUNTIFS(Tests!$B:$B,$A12,Tests!$H:$H,"Fail") -> 0 | E12: =COUNTIFS(Tests!$B:$B,$A12,Tests!$H:$H,"Blocked") -> 0 | F12: =COUNTIFS(Tests!$B:$B,$A12,Tests!$H:$H,"N/A") -> 0 | G12: =COUNTIFS(Tests!$B:$B,$A12,Tests!$H:$H,"Not run") -> 8 | H12: =IF(B12=0,0,(B12-G12)/B12) -> 0
A13: 11 Dashboard | B13: =COUNTIF(Tests!$B:$B,$A13) -> 15 | C13: =COUNTIFS(Tests!$B:$B,$A13,Tests!$H:$H,"Pass") -> 0 | D13: =COUNTIFS(Tests!$B:$B,$A13,Tests!$H:$H,"Fail") -> 0 | E13: =COUNTIFS(Tests!$B:$B,$A13,Tests!$H:$H,"Blocked") -> 0 | F13: =COUNTIFS(Tests!$B:$B,$A13,Tests!$H:$H,"N/A") -> 0 | G13: =COUNTIFS(Tests!$B:$B,$A13,Tests!$H:$H,"Not run") -> 15 | H13: =IF(B13=0,0,(B13-G13)/B13) -> 0
... A36: 34 End-to-end scenarios | B36: =COUNTIF(Tests!$B:$B,$A36) -> 8 | C36: =COUNTIFS(Tests!$B:$B,$A36,Tests!$H:$H,"Pass") -> 0 | D36: =COUNTIFS(Tests!$B:$B,$A36,Tests!$H:$H,"Fail") -> 0 | E36: =COUNTIFS(Tests!$B:$B,$A36,Tests!$H:$H,"Blocked") -> 0 | F36: =COUNTIFS(Tests!$B:$B,$A36,Tests!$H:$H,"N/A") -> 0 | G36: =COUNTIFS(Tests!$B:$B,$A36,Tests!$H:$H,"Not run") -> 8 | H36: =IF(B36=0,0,(B36-G36)/B36) -> 0
A37: Total | B37: =SUM(B2:B36) -> 469 | C37: =SUM(C2:C36) -> 0 | D37: =SUM(D2:D36) -> 0 | E37: =SUM(E2:E36) -> 0 | F37: =SUM(F2:F36) -> 0 | G37: =SUM(G2:G36) -> 469 | H37: =IF(B37=0,0,(B37-G37)/B37) -> 0
A38: Role Access cells | B38: =COUNTA('Role Access'!G2:K29) -> 140 | C38: =COUNTIF('Role Access'!G2:K29,"Pass") -> 0 | D38: =COUNTIF('Role Access'!G2:K29,"Fail") -> 0 | E38: =COUNTIF('Role Access'!G2:K29,"Blocked") -> 0 | F38: =COUNTIF('Role Access'!G2:K29,"N/A") -> 0 | G38: =COUNTIF('Role Access'!G2:K29,"Not run") -> 140 | H38: =IF(B38=0,0,(B38-G38)/B38) -> 0

Sheet Read Me
A1: AMSON - Full System Test Plan
A2: Covers every page, button, filter, tab, sort, search, export, role and business rule in the webapp branch (rules commit 7fdbde9 live on amson-web-app).
A4: How to use
A5: 1. Run on the deployed site (or http://localhost:8080 while Netlify is pending). Use a fresh browser profile per role.
A6: 2. Set Result for each row: Pass / Fail / Blocked / N/A. Leave 'Not run' until tested. On Fail, write what happened in Notes (and add a To-Do row in the Deviation Register).
A7: 3. Do the 'Role Access' sheet once per role. The Summary sheet counts results by section.
A8: 4. Run sections in order: 00 Setup first, 34 End-to-end last. Sections 13-15 and 17-22 need orders and stock created by earlier sections.
A10: Accounts needed (each with a real inbox, because device codes and order emails are sent)
A11: - 2 customers (A, B) - B is used for 'another customer's order' and cart-isolation tests
A12: - 1 Branch Manager, 1 Technical Staff, 1 Sales Staff (create the last two in Staff Management, test 26)
A13: - 1 spare customer and 1 spare staff account to deactivate
A15: Test data needed
... A27: Before go-live: clear test data (test 31) and set REQUIRE_DEVICE_CODE back to true (test 00).

Sheet Tests
A1: ID | B1: Section | C1: Page / where | D1: Log in as | E1: Steps | F1: Expected result | G1: Req | H1: Result | I1: Tester | J1: Date | K1: Notes / bug
A2: T00-01 | B2: 00 Setup & smoke | C2: Site URL | D2: Guest | E2: Open the hosted site (Netlify URL) over https://. | F2: Loads with a padlock (HTTPS); no browser security warning. | G2: REQNF010 | H2: Not run
A3: T00-02 | B3: 00 Setup & smoke | C3: Site URL | D3: Guest | E3: Open index.html. | F3: Redirects to shop/index.html. | H3: Not run
A4: T00-03 | B4: 00 Setup & smoke | C4: Any page | D4: Guest | E4: Open DevTools > Console on the shop home page and reload. | F4: No red errors (Firebase, Cloudinary, EmailJS, Chart.js, jsPDF load). | H4: Not run
A5: T00-04 | B5: 00 Setup & smoke | C5: Any page | D5: Guest | E5: Deploy a small change, then reload normally (no hard refresh). | F5: New version shows (_headers no-cache works). | H5: Not run
A6: T00-05 | B6: 00 Setup & smoke | C6: Firebase console | D6: Branch Manager | E6: Firestore > Rules: compare with firestore.rules on webapp. | F6: Published rules are the latest commit. | G6: REQNF011 | H6: Not run
A7: T00-06 | B7: 00 Setup & smoke | C7: Firebase console | D7: Branch Manager | E7: Authentication > Settings > Authorized domains. | F7: Netlify domain is listed (otherwise login fails on the hosted site). | H7: Not run
A8: T00-07 | B8: 00 Setup & smoke | C8: js/device-trust.js | D8: Branch Manager | E8: Confirm REQUIRE_DEVICE_CODE is true for go-live (false only while testing with fake inboxes). | F8: true on the deployed site. | G8: REQ005 | H8: Not run
A9: T00-08 | B9: 00 Setup & smoke | C9: assets/payment-qr.png | D9: Guest | E9: Open shop/payment.html with an item in the cart. | F9: The branch's real QR Ph image shows (not a placeholder). | G9: REQ028 | H9: Not run
A10: T00-09 | B10: 00 Setup & smoke | C10: js/store-info.js | D10: Guest | E10: Scroll to the footer on any page. | F10: Real store name, address, contact numbers and FDA LTO no. | H10: Not run
A11: T01-01 | B11: 01 Registration | C11: register.html | D11: Guest | E11: Submit with every field empty. | F11: Each required field shows an error; nothing is created. | G11: REQ001 | H11: Not run
A12: T01-02 | B12: 01 Registration | C12: register.html | D12: Guest | E12: First/last name with digits or symbols (e.g. 'Juan2', 'Dela@Cruz'). | F12: Rejected with a name-format message. | G12: REQ001 | H12: Not run
A13: T01-03 | B13: 01 Registration | C13: register.html | D13: Guest | E13: Names with accents, hyphen, period/space (e.g. 'José', 'Dela-Cruz', 'Ma. Clara'). | F13: Accepted. | G13: REQ001 | H13: Not run
A14: T01-04 | B14: 01 Registration | C14: register.html | D14: Guest | E14: Invalid email (e.g. 'juan@', 'juan@gmail', '.juan@gmail.com'). | F14: Rejected. | G14: REQ001 | H14: Not run
A15: T01-05 | B15: 01 Registration | C15: register.html | D15: Guest | E15: Disposable email domain (e.g. @mailnesia.com, @getnada.com). | F15: Rejected as a temporary email. | G15: REQ001 | H15: Not run
A16: T01-06 | B16: 01 Registration | C16: register.html | D16: Guest | E16: Contact no. '0917123456' (10 digits), '+6391712345678', '08171234567'. | F16: Rejected; only 09XXXXXXXXX or +639XXXXXXXXX accepted. | G16: REQ001 | H16: Not run
A17: T01-07 | B17: 01 Registration | C17: register.html | D17: Guest | E17: Contact no. '09171234567' and '+639171234567'. | F17: Both accepted. | G17: REQ001 | H17: Not run
A18: T01-08 | B18: 01 Registration | C18: register.html | D18: Guest | E18: Password 'abcdef', '123456', 'abc123' (no symbol), 'a1!' (too short). | F18: Each rejected: needs 6+ chars with a letter, a digit and a symbol. | G18: REQ001 | H18: Not run
A19: T01-09 | B19: 01 Registration | C19: register.html | D19: Guest | E19: Password 'abc12!' with a different Confirm Password. | F19: Rejected: passwords don't match. | G19: REQ001 | H19: Not run
A20: T01-10 | B20: 01 Registration | C20: register.html | D20: Guest | E20: Click the eye icon on both password fields. | F20: Toggles show/hide. | H20: Not run
A21: T01-11 | B21: 01 Registration | C21: register.html | D21: Guest | E21: Submit without ticking 'I agree' to the Terms. | F21: Blocked with a message. | G21: REQ006 | H21: Not run
A22: T01-12 | B22: 01 Registration | C22: register.html | D22: Guest | E22: Open the Terms link, read, click 'I Have Read and Agree'; also try Close. | F22: Agree ticks the box; Close leaves it unticked. | G22: REQ006 | H22: Not run
A23: T01-13 | B23: 01 Registration | C23: register.html | D23: Guest | E23: Submit without completing reCAPTCHA. | F23: 'Please complete the reCAPTCHA verification.' | G23: REQ003 | H23: Not run
A24: T01-14 | B24: 01 Registration | C24: register.html | D24: Guest | E24: Register with an email that already has an account. | F24: Clear 'already registered' message; no duplicate. | G24: REQ001 | H24: Not run
A25: T01-15 | B25: 01 Registration | C25: register.html | D25: Guest | E25: Register with valid data and a real inbox. | F25: Goes to verify-email.html; 6-digit code arrives by email. | G25: REQ002 | H25: Not run
A26: T01-16 | B26: 01 Registration | C26: verify-email.html | D26: Customer | E26: Type a wrong 6-digit code. | F26: Rejected; account stays unverified. | G26: REQ002 | H26: Not run
A27: T01-17 | B27: 01 Registration | C27: verify-email.html | D27: Customer | E27: Paste the code; also type digit by digit (auto-advance between the 6 boxes). | F27: Both work; correct code verifies and continues. | G27: REQ002 | H27: Not run
A28: T01-18 | B28: 01 Registration | C28: verify-email.html | D28: Customer | E28: Click 'Wrong email? Go back to registration'. | F28: Returns to registration. | H28: Not run
A29: T01-19 | B29: 01 Registration | C29: verify-email.html | D29: Customer | E29: Wait past expiry / request resend (if shown), then use the old code. | F29: Old code rejected; new code works. | G29: REQ002 | H29: Not run
A30: T01-20 | B30: 01 Registration | C30: login.html | D30: Customer | E30: Log in with a registered but unverified account. | F30: Sent to email verification, not into the shop. | G30: REQ002 | H30: Not run
A31: T02-01 | B31: 02 Login & security | C31: login.html | D31: Customer | E31: Log in with correct customer credentials (recognized device). | F31: Lands on the shop as signed in; header shows Account. | G31: REQ043 | H31: Not run
A32: T02-02 | B32: 02 Login & security | C32: login.html | D32: Sales Staff | E32: Log in as Sales Staff. | F32: Lands on admin/pos.html. | G32: REQ121 | H32: Not run
A33: T02-03 | B33: 02 Login & security | C33: login.html | D33: Technical Staff | E33: Log in as Technical Staff. | F33: Lands on admin/dashboard.html. | G33: REQ043 | H33: Not run
A34: T02-04 | B34: 02 Login & security | C34: login.html | D34: Branch Manager | E34: Log in as Branch Manager. | F34: Lands on admin/dashboard.html. | G34: REQ043 | H34: Not run
A35: T02-05 | B35: 02 Login & security | C35: login.html | D35: Guest | E35: Wrong password once. | F35: Generic error; no hint whether the email exists. | H35: Not run
A36: T02-06 | B36: 02 Login & security | C36: login.html | D36: Guest | E36: Wrong password 5 times in a row for the same email. | F36: Account locked for 2 minutes with a countdown/message. | G36: REQ004 | H36: Not run
A37: T02-07 | B37: 02 Login & security | C37: login.html | D37: Guest | E37: During the lock, try the correct password. | F37: Still refused until 2 minutes pass. | G37: REQ004 | H37: Not run
A38: T02-08 | B38: 02 Login & security | C38: login.html | D38: Guest | E38: After 2 minutes, log in with the correct password. | F38: Works; counter resets. | G38: REQ004 | H38: Not run
A39: T02-09 | B39: 02 Login & security | C39: login.html | D39: Branch Manager | E39: Lockout for staff: 5 wrong passwords on a staff email. | F39: Locked for 2 minutes, same as customers. | G39: REQ045 | H39: Not run
A40: T02-10 | B40: 02 Login & security | C40: login.html | D40: Guest | E40: Submit without reCAPTCHA. | F40: Blocked. | G40: REQ003 | H40: Not run
A41: T02-11 | B41: 02 Login & security | C41: login.html | D41: Guest | E41: Tick 'Remember me', log in, close the browser, reopen. | F41: Still signed in. Without it: signed out after the browser closes. | H41: Not run
A42: T02-12 | B42: 02 Login & security | C42: login.html | D42: Customer | E42: Log in from a new browser / incognito (device not recognized). | F42: 6-digit code emailed; must enter it before continuing. | G42: REQ005 | H42: Not run
A43: T02-13 | B43: 02 Login & security | C43: login.html | D43: Customer | E43: Device code: enter a wrong code 5 times. | F43: Locked out of that code; must resend. | G43: REQ005 | H43: Not run
A44: T02-14 | B44: 02 Login & security | C44: login.html | D44: Customer | E44: Device code: click Resend before 60 s, then after 60 s. | F44: Resend waits 60 s; new code arrives and works. | G44: REQ005 | H44: Not run
A45: T02-15 | B45: 02 Login & security | C45: login.html | D45: Customer | E45: Device code: use a code older than 10 minutes. | F45: Rejected as expired. | G45: REQ005 | H45: Not run
A46: T02-16 | B46: 02 Login & security | C46: login.html | D46: Customer | E46: Device code: click Cancel. | F46: Signs out and returns to login. | H46: Not run
A47: T02-17 | B47: 02 Login & security | C47: login.html | D47: Technical Staff | E47: Staff on a new device. | F47: Also gets the device code; admin pages send an unconfirmed device back to login. | G47: REQ044 | H47: Not run
A48: T02-18 | B48: 02 Login & security | C48: login.html | D48: Customer | E48: Log in with a customer account a staff member deactivated. | F48: Refused with a deactivated message. | G48: REQ117 | H48: Not run
A49: T02-19 | B49: 02 Login & security | C49: login.html | D49: Technical Staff | E49: Log in with a deactivated staff account. | F49: Refused. | G49: REQ118 | H49: Not run
A50: T02-20 | B50: 02 Login & security | C50: login.html | D50: Technical Staff | E50: Deactivate a staff account while that person is logged in elsewhere; have them click any admin page. | F50: They lose access immediately (rules deny; page signs them out). | G50: REQNF011 | H50: Not run
A51: T02-21 | B51: 02 Login & security | C51: forgot-password.html | D51: Guest | E51: Submit an invalid email. | F51: Validation error. | G51: REQ007 | H51: Not run
A52: T02-22 | B52: 02 Login & security | C52: forgot-password.html | D52: Guest | E52: Submit a registered email. | F52: Firebase reset email arrives; link sets a new password; old one stops working. | G52: REQ007 | H52: Not run
A53: T02-23 | B53: 02 Login & security | C53: forgot-password.html | D53: Branch Manager | E53: Reset a staff password the same way. | F53: Works for staff. | G53: REQ046 | H53: Not run
A54: T02-24 | B54: 02 Login & security | C54: forgot-password.html | D54: Guest | E54: Submit an email with no account. | F54: Same neutral message (no account enumeration). | H54: Not run
A55: T03-01 | B55: 03 Shop browsing & filters | C55: shop/index.html | D55: Guest | E55: Open the home page. | F55: Products, categories, banner (if active), navigation and footer show. | G55: REQ008 | H55: Not run
A56: T03-02 | B56: 03 Shop browsing & filters | C56: shop/index.html | D56: Guest | E56: Turn on an Announcement banner in Settings; reload shop pages. | F56: Banner shows on every shop page with the right style. | G56: REQ008 | H56: Not run
A57: T03-03 | B57: 03 Shop browsing & filters | C57: shop/index.html | D57: Guest | E57: Switch banner type to Promotion. | F57: Promotion styling shows. | G57: REQ008 | H57: Not run
A58: T03-04 | B58: 03 Shop browsing & filters | C58: shop/index.html | D58: Guest | E58: Turn the banner off. | F58: Banner disappears on all shop pages. | G58: REQ008 | H58: Not run
A59: T03-05 | B59: 03 Shop browsing & filters | C59: shop/index.html | D59: Guest | E59: Click 'Shop Now' and every 'View All' link. | F59: Goes to products.html. | H59: Not run
A60: T03-06 | B60: 03 Shop browsing & filters | C60: shop/index.html | D60: Guest | E60: Use the 'All Products' menu and each category link in the header. | F60: Products page opens filtered to that category. | G60: REQ009 | H60: Not run
A61: T03-07 | B61: 03 Shop browsing & filters | C61: Header (every shop page) | D61: Guest | E61: Type a product name in the header search on each shop page and press Enter / click the search icon. | F61: Goes to products.html with matching results. | G61: REQ011 | H61: Not run
A62: T03-08 | B62: 03 Shop browsing & filters | C62: Header | D62: Guest | E62: Header search with a generic name (e.g. 'paracetamol'). | F62: Products with that generic name show. | G62: REQ011 | H62: Not run
A63: T03-09 | B63: 03 Shop browsing & filters | C63: Header | D63: Guest | E63: Header search with nonsense text. | F63: 'No products found' message. | G63: REQ012 | H63: Not run
A64: T03-10 | B64: 03 Shop browsing & filters | C64: shop/products.html | D64: Guest | E64: Open with no filters. | F64: Only Active, online-available products; each card shows name, price, quantity in stock. | G64: REQ009 | H64: Not run
A65: T03-11 | B65: 03 Shop browsing & filters | C65: shop/products.html | D65: Guest | E65: Category: tick 'All'. | F65: All categories shown; other boxes cleared. | G65: REQ010 | H65: Not run
A66: T03-12 | B66: 03 Shop browsing & filters | C66: shop/products.html | D66: Guest | E66: Category: tick each category one at a time (Generics, Branded, Drugstore (Per Piece), Medical Supplies, and any other). | F66: Only that category's products show for each. | G66: REQ010 | H66: Not run
A67: T03-13 | B67: 03 Shop browsing & filters | C67: shop/products.html | D67: Guest | E67: Category: tick two categories together. | F67: Products from both show; 'All' unticks. | G67: REQ010 | H67: Not run
A68: T03-14 | B68: 03 Shop browsing & filters | C68: shop/products.html | D68: Guest | E68: Category: untick everything. | F68: Falls back to All (or clear empty-state), not a broken page. | G68: REQ010 | H68: Not run
A69: T03-15 | B69: 03 Shop browsing & filters | C69: shop/products.html | D69: Guest | E69: Price: Min only (e.g. 100) > Search. | F69: Only products >= 100. | G69: REQ010 | H69: Not run
A70: T03-16 | B70: 03 Shop browsing & filters | C70: shop/products.html | D70: Guest | E70: Price: Max only (e.g. 50) > Search. | F70: Only products <= 50. | G70: REQ010 | H70: Not run
A71: T03-17 | B71: 03 Shop browsing & filters | C71: shop/products.html | D71: Guest | E71: Price: Min 50, Max 200. | F71: Only products 50-200 inclusive. | G71: REQ010 | H71: Not run
... A76: T03-22 | B76: 03 Shop browsing & filters | C76: shop/products.html | D76: Guest | E76: Stock: 'Out of stock'. | F76: Only out-of-stock products, with an Out of Stock badge; can't add to cart. | G76: REQ010 | H76: Not run
A77: T03-23 | B77: 03 Shop browsing & filters | C77: shop/products.html | D77: Guest | E77: Sort: Name (A-Z). | F77: Alphabetical ascending. | H77: Not run
A78: T03-24 | B78: 03 Shop browsing & filters | C78: shop/products.html | D78: Guest | E78: Sort: Name (Z-A). | F78: Alphabetical descending. | H78: Not run
A79: T03-25 | B79: 03 Shop browsing & filters | C79: shop/products.html | D79: Guest | E79: Sort: Price (Low-High). | F79: Cheapest first. | H79: Not run
A80: T03-26 | B80: 03 Shop browsing & filters | C80: shop/products.html | D80: Guest | E80: Sort: Price (High-Low). | F80: Most expensive first. | H80: Not run
A81: T03-27 | B81: 03 Shop browsing & filters | C81: shop/products.html | D81: Guest | E81: Combine: one category + price range + In stock only + Price (Low-High) + a search word. | F81: All filters apply together. | G81: REQ010 | H81: Not run
A82: T03-28 | B82: 03 Shop browsing & filters | C82: shop/products.html | D82: Guest | E82: Combination that matches nothing. | F82: 'No products found' message. | G82: REQ012 | H82: Not run
A83: T03-29 | B83: 03 Shop browsing & filters | C83: shop/products.html | D83: Guest | E83: Change a filter, go to page 2, then change a filter again. | F83: Pagination resets to page 1; page count matches results. | H83: Not run
A84: T03-30 | B84: 03 Shop browsing & filters | C84: shop/products.html | D84: Guest | E84: Pagination: next/previous/each page number. | F84: Correct products per page; no duplicates or gaps. | H84: Not run
A85: T03-31 | B85: 03 Shop browsing & filters | C85: shop/products.html | D85: Guest | E85: Mark a product Inactive or untick 'Available online' in admin. | F85: It disappears from the shop. | G85: REQ009 | H85: Not run
A86: T03-32 | B86: 03 Shop browsing & filters | C86: shop/products.html | D86: Guest | E86: A product with only near-expiry (within 6 months) stock. | F86: Shows as out of stock online. | G86: REQ066 | H86: Not run
A87: T03-33 | B87: 03 Shop browsing & filters | C87: shop/products.html | D87: Guest | E87: Quick view (if shown on cards). | F87: Shows name, price, stock, dosage notes. | G87: REQ013 | H87: Not run
A88: T03-34 | B88: 03 Shop browsing & filters | C88: shop/product-details.html | D88: Guest | E88: Open a product. | F88: Name, description, price, stock, dosage/usage notes and image. | G88: REQ013 | H88: Not run
A89: T03-35 | B89: 03 Shop browsing & filters | C89: shop/product-details.html | D89: Guest | E89: Open an Rx product. | F89: Rx badge and prescription notice. | G89: REQ021 | H89: Not run
A90: T03-36 | B90: 03 Shop browsing & filters | C90: shop/product-details.html | D90: Guest | E90: Quantity: set above stock; set 0 or negative. | F90: Capped at stock; 0/negative refused. | G90: REQ015 | H90: Not run
A91: T03-37 | B91: 03 Shop browsing & filters | C91: shop/product-details.html | D91: Guest | E91: Add to cart as a guest. | F91: Toast shows; cart count updates. | G91: REQ014 | H91: Not run
A92: T03-38 | B92: 03 Shop browsing & filters | C92: shop/product-details.html | D92: Guest | E92: Open product-details.html with a bad or missing id. | F92: Friendly 'not found', no crash. | G92: REQNF014 | H92: Not run
A93: T04-01 | B93: 04 Cart | C93: shop/cart.html | D93: Guest | E93: Add 3 different products; open cart. | F93: All 3 with correct prices and line totals. | G93: REQ015 | H93: Not run
A94: T04-02 | B94: 04 Cart | C94: shop/cart.html | D94: Guest | E94: Increase / decrease quantity; type a quantity. | F94: Running total updates immediately; can't exceed stock. | G94: REQ016 | H94: Not run
A95: T04-03 | B95: 04 Cart | C95: shop/cart.html | D95: Guest | E95: Remove an item. | F95: Item removed; total updates. | G95: REQ015 | H95: Not run
A96: T04-04 | B96: 04 Cart | C96: shop/cart.html | D96: Guest | E96: Untick one item's checkbox; use 'Select all'. | F96: Total counts only ticked items; Select all ticks/unticks all. | G96: REQ016 | H96: Not run
A97: T04-05 | B97: 04 Cart | C97: shop/cart.html | D97: Guest | E97: Proceed to Checkout as a guest. | F97: Asked to log in/register first. | H97: Not run
A98: T04-06 | B98: 04 Cart | C98: shop/cart.html | D98: Customer | E98: As guest add items, then log in. | F98: Guest cart merges into the account cart. | G98: REQ014 | H98: Not run
A99: T04-07 | B99: 04 Cart | C99: shop/cart.html | D99: Customer | E99: Log in on a second browser with the same account. | F99: Same cart shows (saved on the account). | G99: REQ014 | H99: Not run
A100: T04-08 | B100: 04 Cart | C100: shop/cart.html | D100: Customer | E100: Log out, then log in as a different customer on the same browser. | F100: First customer's cart does not show. | G100: REQ014 | H100: Not run
A101: T04-09 | B101: 04 Cart | C101: shop/cart.html | D101: Customer | E101: Product goes out of stock while in the cart. | F101: Cart flags it and blocks checkout for that item. | G101: REQ050 | H101: Not run
A102: T04-10 | B102: 04 Cart | C102: shop/cart.html | D102: Customer | E102: Empty cart. | F102: Empty-state message with Browse Products. | H102: Not run
A103: T05-01 | B103: 05 Checkout | C103: shop/checkout.html | D103: Customer | E103: Open checkout with a non-Rx cart. | F103: Name, email, contact prefilled; saved address prefilled. | G103: REQ017 | H103: Not run
A104: T05-02 | B104: 05 Checkout | C104: shop/checkout.html | D104: Customer | E104: Clear the street address and try 'Proceed to Payment'. | F104: Blocked until the address is complete. | G104: REQ019 | H104: Not run
...

Sheet Role Access
A1: Page | B1: Expected: Guest | C1: Expected: Customer | D1: Expected: Sales Staff | E1: Expected: Technical Staff | F1: Expected: Branch Manager | G1: Result: Guest | H1: Result: Customer | I1: Result: Sales Staff | J1: Result: Technical Staff | K1: Result: Branch Manager | L1: Notes
A2: admin/dashboard.html | B2: Sent to login | C2: Sent to shop home | D2: "No access" alert, then POS | E2: Opens | F2: Opens | G2: Not run | H2: Not run | I2: Not run | J2: Not run | K2: Not run
A3: admin/pos.html | B3: Sent to login | C3: Sent to shop home | D3: Opens | E3: Opens | F3: Opens | G3: Not run | H3: Not run | I3: Not run | J3: Not run | K3: Not run
A4: admin/products.html | B4: Sent to login | C4: Sent to shop home | D4: Opens (view-only) | E4: Opens | F4: Opens | G4: Not run | H4: Not run | I4: Not run | J4: Not run | K4: Not run
A5: admin/online-orders.html | B5: Sent to login | C5: Sent to shop home | D5: "No access" alert, then POS | E5: Opens | F5: Opens | G5: Not run | H5: Not run | I5: Not run | J5: Not run | K5: Not run
A6: admin/inventory.html | B6: Sent to login | C6: Sent to shop home | D6: "No access" alert, then POS | E6: Opens | F6: Opens | G6: Not run | H6: Not run | I6: Not run | J6: Not run | K6: Not run
A7: admin/suppliers.html | B7: Sent to login | C7: Sent to shop home | D7: "No access" alert, then POS | E7: Opens | F7: Opens | G7: Not run | H7: Not run | I7: Not run | J7: Not run | K7: Not run
A8: admin/customer-accounts.html | B8: Sent to login | C8: Sent to shop home | D8: "No access" alert, then POS | E8: Opens | F8: Opens | G8: Not run | H8: Not run | I8: Not run | J8: Not run | K8: Not run
A9: admin/wholesale-accounts.html | B9: Sent to login | C9: Sent to shop home | D9: "No access" alert, then POS | E9: Opens | F9: Opens | G9: Not run | H9: Not run | I9: Not run | J9: Not run | K9: Not run
A10: admin/audit-log.html | B10: Sent to login | C10: Sent to shop home | D10: "No access" alert, then POS | E10: Opens | F10: Opens | G10: Not run | H10: Not run | I10: Not run | J10: Not run | K10: Not run
A11: admin/notifications.html | B11: Sent to login | C11: Sent to shop home | D11: "No access" alert, then POS | E11: Opens | F11: Opens | G11: Not run | H11: Not run | I11: Not run | J11: Not run | K11: Not run
A12: admin/live-chat.html | B12: Sent to login | C12: Sent to shop home | D12: "No access" alert, then POS | E12: Opens | F12: Opens | G12: Not run | H12: Not run | I12: Not run | J12: Not run | K12: Not run
A13: admin/reports.html | B13: Sent to login | C13: Sent to shop home | D13: "No access" alert, then POS | E13: Opens | F13: Opens | G13: Not run | H13: Not run | I13: Not run | J13: Not run | K13: Not run
... A29: shop/account-settings.html | B29: Asks to log in | C29: Opens | D29: As designed (staff are not customers) | E29: As designed | F29: As designed | G29: Not run | H29: Not run | I29: Not run | J29: Not run | K29: Not run
A31: Clear Test Data also switches itself off on 2026-11-15 (page refused for everyone after that).
